momo_sdk/__init__.py
momo_sdk/momo.py
mtn_momo_sdk-0.1.6.dist-info/licenses/LICENSE
mtn_momo_sdk-0.1.6.dist-info/METADATA
mtn_momo_sdk-0.1.6.dist-info/WHEEL
mtn_momo_sdk-0.1.6.dist-info/top_level.txt
mtn_momo_sdk-0.1.6.dist-info/RECORD
