Metadata-Version: 2.4
Name: mtn-momo-sdk
Version: 0.1.6
Summary: Python SDK for MTN Uganda MoMo API integration
Home-page: https://github.com/brucekyl/momo-sdk
Author: Bruce Bagarukayo
Author-email: Bruce Bagarukayo <bbagarukayo5@gmail.com>
License: MIT
Requires-Python: >=3.7
License-File: LICENSE
Requires-Dist: requests
Requires-Dist: setuptools
Dynamic: author
Dynamic: home-page
Dynamic: license-file
Dynamic: requires-python
